md_spreadsheet_parser/__init__.py
md_spreadsheet_parser/cli.py
md_spreadsheet_parser/converters.py
md_spreadsheet_parser/excel.py
md_spreadsheet_parser/generator.py
md_spreadsheet_parser/loader.py
md_spreadsheet_parser/models.py
md_spreadsheet_parser/parsing.py
md_spreadsheet_parser/py.typed
md_spreadsheet_parser/pydantic_adapter.py
md_spreadsheet_parser/schemas.py
md_spreadsheet_parser/utils.py
md_spreadsheet_parser/validation.py
md_spreadsheet_parser-1.2.0.dist-info/METADATA
md_spreadsheet_parser-1.2.0.dist-info/WHEEL
md_spreadsheet_parser-1.2.0.dist-info/entry_points.txt
md_spreadsheet_parser-1.2.0.dist-info/licenses/LICENSE
md_spreadsheet_parser-1.2.0.dist-info/RECORD
