Metadata-Version: 2.4
Name: md-spreadsheet-parser
Version: 1.2.0
Summary: A robust, zero-dependency Python library for parsing, validating, and manipulating Markdown tables, including conversion from Excel to Markdown.
Project-URL: Homepage, https://f-y.github.io/md-spreadsheet-parser/
Project-URL: Repository, https://github.com/f-y/md-spreadsheet-parser
Project-URL: Issues, https://github.com/f-y/md-spreadsheet-parser/issues
Project-URL: Changelog, https://github.com/f-y/md-spreadsheet-parser/releases
Author: f-y
License: MIT License
License-File: LICENSE
Keywords: cli,conversion,csv,dataframe,excel,markdown,pandas,parser,spreadsheet,table,zero-dependency
Classifier: Development Status :: 5 - Production/Stable
Classifier: Intended Audience :: Developers
Classifier: License :: OSI Approved :: MIT License
Classifier: Operating System :: OS Independent
Classifier: Programming Language :: Python :: 3
Classifier: Programming Language :: Python :: 3.12
Classifier: Topic :: Software Development :: Libraries :: Python Modules
Classifier: Topic :: Text Processing :: Markup :: Markdown
Requires-Python: >=3.10
